smds/__init__.py
smds/smds.py
smds/pipeline/__init__.py
smds/pipeline/dashboard.py
smds/pipeline/discovery_pipeline.py
smds/pipeline/open_dashboard.py
smds/pipeline/run_pipeline.py
smds/pipeline/helpers/hash.py
smds/pipeline/helpers/interactive_plots.py
smds/pipeline/helpers/plots.py
smds/pipeline/helpers/styling.py
smds/shapes/__init__.py
smds/shapes/base_shape.py
smds/shapes/continuous_shapes/__init__.py
smds/shapes/continuous_shapes/circular.py
smds/shapes/continuous_shapes/euclidean.py
smds/shapes/continuous_shapes/klein_bottle.py
smds/shapes/continuous_shapes/log_linear.py
smds/shapes/continuous_shapes/semicircular.py
smds/shapes/continuous_shapes/spiral_shape.py
smds/shapes/coordinates/__init__.py
smds/shapes/coordinates/base_coordinates.py
smds/shapes/coordinates/cartesian_coordinates.py
smds/shapes/coordinates/polar_coordinates.py
smds/shapes/discrete_shapes/__init__.py
smds/shapes/discrete_shapes/chain.py
smds/shapes/discrete_shapes/cluster.py
smds/shapes/discrete_shapes/discrete_circular.py
smds/shapes/discrete_shapes/hierarchical.py
smds/shapes/spatial_shapes/__init__.py
smds/shapes/spatial_shapes/cylindrical.py
smds/shapes/spatial_shapes/geodesic.py
smds/shapes/spatial_shapes/spherical.py
smds/stress/__init__.py
smds/stress/kl_divergence.py
smds/stress/non_metric_stress.py
smds/stress/normalized_stress.py
smds/stress/scale_normalized_stress.py
smds/stress/shepard_goodness_score.py
smds/stress/stress_metrics.py
supervised_multidimensional_scaling-0.9.1.dist-info/METADATA
supervised_multidimensional_scaling-0.9.1.dist-info/WHEEL
supervised_multidimensional_scaling-0.9.1.dist-info/licenses/LICENSE
supervised_multidimensional_scaling-0.9.1.dist-info/licenses/NOTICE.txt
supervised_multidimensional_scaling-0.9.1.dist-info/RECORD
